cfenv/__init__.py
cfenv-0.5.3.dist-info/DESCRIPTION.rst
cfenv-0.5.3.dist-info/METADATA
cfenv-0.5.3.dist-info/RECORD
cfenv-0.5.3.dist-info/WHEEL
cfenv-0.5.3.dist-info/metadata.json
cfenv-0.5.3.dist-info/top_level.txt
