Metadata-Version: 2.0
Name: cfenv
Version: 0.5.3
Summary: Python wrapper for Cloud Foundry environments
Home-page: https://github.com/jmcarp/py-cfenv
Author: Joshua Carp
Author-email: jm.carp@gmail.com
License: MIT
Keywords: cloud foundry
Platform: UNKNOWN
Classifier: Development Status :: 2 - Pre-Alpha
Classifier: Intended Audience :: Developers
Classifier: License :: OSI Approved :: MIT License
Classifier: Natural Language :: English
Classifier: Programming Language :: Python :: 2
Classifier: Programming Language :: Python :: 2.7
Classifier: Programming Language :: Python :: 3
Classifier: Programming Language :: Python :: 3.3
Classifier: Programming Language :: Python :: 3.4
Classifier: Programming Language :: Python :: 3.5
Requires-Dist: furl (>=0.4.8)
